aigents/__init__.py
aigents/client.py
aigents/exceptions.py
aigents/models.py
aigents/resources/__init__.py
aigents/resources/applications.py
aigents/resources/chat.py
aigents_sdk-0.1.0.dist-info/licenses/LICENSE
aigents_sdk-0.1.0.dist-info/METADATA
aigents_sdk-0.1.0.dist-info/WHEEL
aigents_sdk-0.1.0.dist-info/top_level.txt
aigents_sdk-0.1.0.dist-info/RECORD
