Metadata-Version: 2.4
Name: aigents-sdk
Version: 0.1.0
Summary: Official Python client library for AIgents AI platform
Home-page: https://github.com/aigents/aigents-python
Author: AIgents Team
Author-email: AIgents Team <support@aigents.co>
Project-URL: Homepage, https://aigents.co
Project-URL: Documentation, https://docs.aigents.co
Project-URL: Repository, https://github.com/aigents/aigents-python
Project-URL: Bug Reports, https://github.com/aigents/aigents-python/issues
Keywords: ai,artificial-intelligence,chatbot,llm,gpt,agents,tools
Classifier: Development Status :: 4 - Beta
Classifier: Intended Audience :: Developers
Classifier: License :: OSI Approved :: MIT License
Classifier: Operating System :: OS Independent
Classifier: Programming Language :: Python :: 3
Classifier: Programming Language :: Python :: 3.8
Classifier: Programming Language :: Python :: 3.9
Classifier: Programming Language :: Python :: 3.10
Classifier: Programming Language :: Python :: 3.11
Classifier: Programming Language :: Python :: 3.12
Classifier: Topic :: Software Development :: Libraries :: Python Modules
Classifier: Topic :: Scientific/Engineering :: Artificial Intelligence
Requires-Python: >=3.8
License-File: LICENSE
Requires-Dist: requests>=2.28.0
Requires-Dist: typing-extensions>=4.0.0
Provides-Extra: dev
Requires-Dist: pytest>=7.0.0; extra == "dev"
Requires-Dist: pytest-cov>=4.0.0; extra == "dev"
Requires-Dist: black>=22.0.0; extra == "dev"
Requires-Dist: flake8>=5.0.0; extra == "dev"
Requires-Dist: mypy>=1.0.0; extra == "dev"
Dynamic: author
Dynamic: home-page
Dynamic: license-file
Dynamic: requires-python
